{"kind": "Listing", "data": {"after": null, "dist": 15, "modhash": "", "geo_filter": "", "children": [{"kind": "t3", "data": {"approved_at_utc": null, "subreddit": "dataengineering", "selftext": "It\u2019s understood that data engineering is a subset of software engineering, but as time goes on, it seems there are more distinctions forming around different types?\n\nFor example, Starbucks was hiring for a senior data engineer who would focus more on semantics, ontologies, metadata, cataloging, and master data management. It didn\u2019t mention building pipelines, but was expected to have previous experience doing so.\n\nThen you have data engineers who are effectively data-flavored forms of devops, and focus more on platform engineering. \n\nLikewise, business focused front-end data engineers, who were previously labeled business intelligence engineers, are now commonly referred to as analytics engineers.\n\nLastly, what about data engineers who aren\u2019t necessarily creating new pipelines, but optimizing existing ones? Or data engineers who work in shops who have opted to buy (Fivetran, ADF, paid Airbyte) instead of build?\n\nJust curious is all.", "author_fullname": "t2_3uoce3bn", "saved": false, "mod_reason_title": null, "gilded": 0, "clicked": false, "title": "In your opinion, are there different types/classes of data engineers?", "link_flair_richtext": [], "subreddit_name_prefixed": "r/dataengineering", "hidden": false, "pwls": 6, "link_flair_css_class": "", "downs": 0, "thumbnail_height": null, "top_awarded_type": null, "hide_score": false, "name": "t3_1909k7c", "quarantine": false, "link_flair_text_color": "light", "upvote_ratio": 0.75, "author_flair_background_color": null, "subreddit_type": "public", "ups": 16, "total_awards_received": 0, "media_embed": {}, "thumbnail_width": null, "author_flair_template_id": null, "is_original_content": false, "user_reports": [], "secure_media": null, "is_reddit_media_domain": false, "is_meta": false, "category": null, "secure_media_embed": {}, "link_flair_text": "Discussion", "can_mod_post": false, "score": 16, "approved_by": null, "is_created_from_ads_ui": false, "author_premium": false, "thumbnail": "self", "edited": false, "author_flair_css_class": null, "author_flair_richtext": [], "gildings": {}, "content_categories": null, "is_self": true, "mod_note": null, "created": 1704573604.0, "link_flair_type": "text", "wls": 6, "removed_by_category": null, "banned_by": null, "author_flair_type": "text", "domain": "self.dataengineering", "allow_live_comments": false, "selftext_html": "&lt;!-- SC_OFF --&gt;&lt;div class=\"md\"&gt;&lt;p&gt;It\u2019s understood that data engineering is a subset of software engineering, but as time goes on, it seems there are more distinctions forming around different types?&lt;/p&gt;\n\n&lt;p&gt;For example, Starbucks was hiring for a senior data engineer who would focus more on semantics, ontologies, metadata, cataloging, and master data management. It didn\u2019t mention building pipelines, but was expected to have previous experience doing so.&lt;/p&gt;\n\n&lt;p&gt;Then you have data engineers who are effectively data-flavored forms of devops, and focus more on platform engineering. &lt;/p&gt;\n\n&lt;p&gt;Likewise, business focused front-end data engineers, who were previously labeled business intelligence engineers, are now commonly referred to as analytics engineers.&lt;/p&gt;\n\n&lt;p&gt;Lastly, what about data engineers who aren\u2019t necessarily creating new pipelines, but optimizing existing ones? Or data engineers who work in shops who have opted to buy (Fivetran, ADF, paid Airbyte) instead of build?&lt;/p&gt;\n\n&lt;p&gt;Just curious is all.&lt;/p&gt;\n&lt;/div&gt;&lt;!-- SC_ON --&gt;", "likes": null, "suggested_sort": null, "banned_at_utc": null, "view_count": null, "archived": false, "no_follow": false, "is_crosspostable": false, "pinned": false, "over_18": false, "all_awardings": [], "awarders": [], "media_only": false, "link_flair_template_id": "92b74b58-aaca-11eb-b160-0e6181e3773f", "can_gild": false, "spoiler": false, "locked": false, "author_flair_text": null, "treatment_tags": [], "visited": false, "removed_by": null, "num_reports": null, "distinguished": null, "subreddit_id": "t5_36en4", "author_is_blocked": false, "mod_reason_by": null, "removal_reason": null, "link_flair_background_color": "#ff4500", "id": "1909k7c", "is_robot_indexable": true, "report_reasons": null, "author": "Tender_Figs", "discussion_type": null, "num_comments": 18, "send_replies": true, "whitelist_status": "all_ads", "contest_mode": false, "mod_reports": [], "author_patreon_flair": false, "author_flair_text_color": null, "permalink": "/r/dataengineering/comments/1909k7c/in_your_opinion_are_there_different_typesclasses/", "parent_whitelist_status": "all_ads", "stickied": false, "url": "https://old.reddit.com/r/dataengineering/comments/1909k7c/in_your_opinion_are_there_different_typesclasses/", "subreddit_subscribers": 151037, "created_utc": 1704573604.0, "num_crossposts": 0, "media": null, "is_video": false}}, {"kind": "t3", "data": {"approved_at_utc": null, "subreddit": "dataengineering", "selftext": "Hi,\n\nThere is an application which is creating/updating/deleting processed csv files in AWS s3 bucket. I need to design a system which can update a SQL table based on data which is present in the bucket in near real time. This table will act as a source for a PowerBI dashboard.\n\nFoe example - let's say there are 10 csv files for which I have created a RDS table. Now, if the application deletes 2 files, then the data for those files should be removed from the RDS table. If the application overwrites a file, then the data should be updated  and so on.\n\nOne of the potential solution I have in my mind is to create a lambda with trigger on the bucket which will copy data from s3 bucket to table. For deleting, I. can execute a delete query using cursor operations. However, this doesn't seems very efficient.\n\nAnother solution I was thinking is to setup a glue crawler and create a athena table. But this might not be very cost efficient since it charges per query execution.\n\nI am not a full fledged Data Engineer. Would love to hear other's ideas.\n\nThanks", "author_fullname": "t2_82wdt351", "saved": false, "mod_reason_title": null, "gilded": 0, "clicked": false, "title": "Best method to update SQL table from AWS S3", "link_flair_richtext": [], "subreddit_name_prefixed": "r/dataengineering", "hidden": false, "pwls": 6, "link_flair_css_class": "", "downs": 0, "thumbnail_height": null, "top_awarded_type": null, "hide_score": false, "name": "t3_190qv2a", "quarantine": false, "link_flair_text_color": "light", "upvote_ratio": 0.75, "author_flair_background_color": null, "subreddit_type": "public", "ups": 6, "total_awards_received": 0, "media_embed": {}, "thumbnail_width": null, "author_flair_template_id": null, "is_original_content": false, "user_reports": [], "secure_media": null, "is_reddit_media_domain": false, "is_meta": false, "category": null, "secure_media_embed": {}, "link_flair_text": "Discussion", "can_mod_post": false, "score": 6, "approved_by": null, "is_created_from_ads_ui": false, "author_premium": false, "thumbnail": "self", "edited": false, "author_flair_css_class": null, "author_flair_richtext": [], "gildings": {}, "content_categories": null, "is_self": true, "mod_note": null, "created": 1704629574.0, "link_flair_type": "text", "wls": 6, "removed_by_category": null, "banned_by": null, "author_flair_type": "text", "domain": "self.dataengineering", "allow_live_comments": false, "selftext_html": "&lt;!-- SC_OFF --&gt;&lt;div class=\"md\"&gt;&lt;p&gt;Hi,&lt;/p&gt;\n\n&lt;p&gt;There is an application which is creating/updating/deleting processed csv files in AWS s3 bucket. I need to design a system which can update a SQL table based on data which is present in the bucket in near real time. This table will act as a source for a PowerBI dashboard.&lt;/p&gt;\n\n&lt;p&gt;Foe example - let&amp;#39;s say there are 10 csv files for which I have created a RDS table. Now, if the application deletes 2 files, then the data for those files should be removed from the RDS table. If the application overwrites a file, then the data should be updated  and so on.&lt;/p&gt;\n\n&lt;p&gt;One of the potential solution I have in my mind is to create a lambda with trigger on the bucket which will copy data from s3 bucket to table. For deleting, I. can execute a delete query using cursor operations. However, this doesn&amp;#39;t seems very efficient.&lt;/p&gt;\n\n&lt;p&gt;Another solution I was thinking is to setup a glue crawler and create a athena table. But this might not be very cost efficient since it charges per query execution.&lt;/p&gt;\n\n&lt;p&gt;I am not a full fledged Data Engineer. Would love to hear other&amp;#39;s ideas.&lt;/p&gt;\n\n&lt;p&gt;Thanks&lt;/p&gt;\n&lt;/div&gt;&lt;!-- SC_ON --&gt;", "likes": null, "suggested_sort": null, "banned_at_utc": null, "view_count": null, "archived": false, "no_follow": false, "is_crosspostable": false, "pinned": false, "over_18": false, "all_awardings": [], "awarders": [], "media_only": false, "link_flair_template_id": "92b74b58-aaca-11eb-b160-0e6181e3773f", "can_gild": false, "spoiler": false, "locked": false, "author_flair_text": null, "treatment_tags": [], "visited": false, "removed_by": null, "num_reports": null, "distinguished": null, "subreddit_id": "t5_36en4", "author_is_blocked": false, "mod_reason_by": null, "removal_reason": null, "link_flair_background_color": "#ff4500", "id": "190qv2a", "is_robot_indexable": true, "report_reasons": null, "author": "Wayne_dj", "discussion_type": null, "num_comments": 10, "send_replies": true, "whitelist_status": "all_ads", "contest_mode": false, "mod_reports": [], "author_patreon_flair": false, "author_flair_text_color": null, "permalink": "/r/dataengineering/comments/190qv2a/best_method_to_update_sql_table_from_aws_s3/", "parent_whitelist_status": "all_ads", "stickied": false, "url": "https://old.reddit.com/r/dataengineering/comments/190qv2a/best_method_to_update_sql_table_from_aws_s3/", "subreddit_subscribers": 151037, "created_utc": 1704629574.0, "num_crossposts": 0, "media": null, "is_video": false}}, {"kind": "t3", "data": {"approved_at_utc": null, "subreddit": "dataengineering", "selftext": "Howdy compadres,\n\nI have an upcoming first round technical Meta de interview. I'm curious if anyone have any info on the general difficulty of the questions? Would stratascratch mediums cover it or should I amp it up? A lot of info on the meta swe interviews out there but not a ton on the de ones (at least for this specific stage).\n\nI'm fairly confident I can handle most joins/aggregations etc.. but you know the deal, interviews like this make you question your skillset.", "author_fullname": "t2_13wepq", "saved": false, "mod_reason_title": null, "gilded": 0, "clicked": false, "title": "Meta Round 1 Technical Interview", "link_flair_richtext": [], "subreddit_name_prefixed": "r/dataengineering", "hidden": false, "pwls": 6, "link_flair_css_class": "", "downs": 0, "thumbnail_height": null, "top_awarded_type": null, "hide_score": false, "name": "t3_190vs11", "quarantine": false, "link_flair_text_color": "light", "upvote_ratio": 0.8, "author_flair_background_color": null, "subreddit_type": "public", "ups": 9, "total_awards_received": 0, "media_embed": {}, "thumbnail_width": null, "author_flair_template_id": null, "is_original_content": false, "user_reports": [], "secure_media": null, "is_reddit_media_domain": false, "is_meta": false, "category": null, "secure_media_embed": {}, "link_flair_text": "Interview", "can_mod_post": false, "score": 9, "approved_by": null, "is_created_from_ads_ui": false, "author_premium": false, "thumbnail": "self", "edited": false, "author_flair_css_class": null, "author_flair_richtext": [], "gildings": {}, "content_categories": null, "is_self": true, "mod_note": null, "created": 1704644589.0, "link_flair_type": "text", "wls": 6, "removed_by_category": null, "banned_by": null, "author_flair_type": "text", "domain": "self.dataengineering", "allow_live_comments": false, "selftext_html": "&lt;!-- SC_OFF --&gt;&lt;div class=\"md\"&gt;&lt;p&gt;Howdy compadres,&lt;/p&gt;\n\n&lt;p&gt;I have an upcoming first round technical Meta de interview. I&amp;#39;m curious if anyone have any info on the general difficulty of the questions? Would stratascratch mediums cover it or should I amp it up? A lot of info on the meta swe interviews out there but not a ton on the de ones (at least for this specific stage).&lt;/p&gt;\n\n&lt;p&gt;I&amp;#39;m fairly confident I can handle most joins/aggregations etc.. but you know the deal, interviews like this make you question your skillset.&lt;/p&gt;\n&lt;/div&gt;&lt;!-- SC_ON --&gt;", "likes": null, "suggested_sort": null, "banned_at_utc": null, "view_count": null, "archived": false, "no_follow": false, "is_crosspostable": false, "pinned": false, "over_18": false, "all_awardings": [], "awarders": [], "media_only": false, "link_flair_template_id": "0922f6d6-a952-11eb-91e4-0e23043eebfb", "can_gild": false, "spoiler": false, "locked": false, "author_flair_text": null, "treatment_tags": [], "visited": false, "removed_by": null, "num_reports": null, "distinguished": null, "subreddit_id": "t5_36en4", "author_is_blocked": false, "mod_reason_by": null, "removal_reason": null, "link_flair_background_color": "#ffb000", "id": "190vs11", "is_robot_indexable": true, "report_reasons": null, "author": "bolognaisass", "discussion_type": null, "num_comments": 9, "send_replies": true, "whitelist_status": "all_ads", "contest_mode": false, "mod_reports": [], "author_patreon_flair": false, "author_flair_text_color": null, "permalink": "/r/dataengineering/comments/190vs11/meta_round_1_technical_interview/", "parent_whitelist_status": "all_ads", "stickied": false, "url": "https://old.reddit.com/r/dataengineering/comments/190vs11/meta_round_1_technical_interview/", "subreddit_subscribers": 151037, "created_utc": 1704644589.0, "num_crossposts": 0, "media": null, "is_video": false}}, {"kind": "t3", "data": {"approved_at_utc": null, "subreddit": "dataengineering", "selftext": "I have completed my masters in computer science, Currently aiming to get a full time job as Data Analyst or Data Analytics roll. I am looking forward to build my Git Hub Profile with projects that will be helpful for my interview and showcase the skills required for the respected roles.  \nI have started watching some youtube projects but i feel everyone will be doing the same and just copy pasting for their GitHub profile. I am ready to buy courses around $40 to $100 and learn the skills with really good projects.\n\nThanks in advance if any one helps me with the links or courses for building my Git Hub profile.", "author_fullname": "t2_kamr5unq", "saved": false, "mod_reason_title": null, "gilded": 0, "clicked": false, "title": "Where to find Good Projects for Github profile in Data Analyst or Analytics.", "link_flair_richtext": [], "subreddit_name_prefixed": "r/dataengineering", "hidden": false, "pwls": 6, "link_flair_css_class": "", "downs": 0, "thumbnail_height": null, "top_awarded_type": null, "hide_score": false, "name": "t3_190f5v2", "quarantine": false, "link_flair_text_color": "light", "upvote_ratio": 0.8, "author_flair_background_color": null, "subreddit_type": "public", "ups": 6, "total_awards_received": 0, "media_embed": {}, "thumbnail_width": null, "author_flair_template_id": null, "is_original_content": false, "user_reports": [], "secure_media": null, "is_reddit_media_domain": false, "is_meta": false, "category": null, "secure_media_embed": {}, "link_flair_text": "Career", "can_mod_post": false, "score": 6, "approved_by": null, "is_created_from_ads_ui": false, "author_premium": false, "thumbnail": "self", "edited": false, "author_flair_css_class": null, "author_flair_richtext": [], "gildings": {}, "content_categories": null, "is_self": true, "mod_note": null, "created": 1704588314.0, "link_flair_type": "text", "wls": 6, "removed_by_category": null, "banned_by": null, "author_flair_type": "text", "domain": "self.dataengineering", "allow_live_comments": false, "selftext_html": "&lt;!-- SC_OFF --&gt;&lt;div class=\"md\"&gt;&lt;p&gt;I have completed my masters in computer science, Currently aiming to get a full time job as Data Analyst or Data Analytics roll. I am looking forward to build my Git Hub Profile with projects that will be helpful for my interview and showcase the skills required for the respected roles.&lt;br/&gt;\nI have started watching some youtube projects but i feel everyone will be doing the same and just copy pasting for their GitHub profile. I am ready to buy courses around $40 to $100 and learn the skills with really good projects.&lt;/p&gt;\n\n&lt;p&gt;Thanks in advance if any one helps me with the links or courses for building my Git Hub profile.&lt;/p&gt;\n&lt;/div&gt;&lt;!-- SC_ON --&gt;", "likes": null, "suggested_sort": null, "banned_at_utc": null, "view_count": null, "archived": false, "no_follow": false, "is_crosspostable": false, "pinned": false, "over_18": false, "all_awardings": [], "awarders": [], "media_only": false, "link_flair_template_id": "069dd614-a7dc-11eb-8e48-0e90f49436a3", "can_gild": false, "spoiler": false, "locked": false, "author_flair_text": null, "treatment_tags": [], "visited": false, "removed_by": null, "num_reports": null, "distinguished": null, "subreddit_id": "t5_36en4", "author_is_blocked": false, "mod_reason_by": null, "removal_reason": null, "link_flair_background_color": "#349e48", "id": "190f5v2", "is_robot_indexable": true, "report_reasons": null, "author": "No_Caregiver5020", "discussion_type": null, "num_comments": 8, "send_replies": true, "whitelist_status": "all_ads", "contest_mode": false, "mod_reports": [], "author_patreon_flair": false, "author_flair_text_color": null, "permalink": "/r/dataengineering/comments/190f5v2/where_to_find_good_projects_for_github_profile_in/", "parent_whitelist_status": "all_ads", "stickied": false, "url": "https://old.reddit.com/r/dataengineering/comments/190f5v2/where_to_find_good_projects_for_github_profile_in/", "subreddit_subscribers": 151037, "created_utc": 1704588314.0, "num_crossposts": 0, "media": null, "is_video": false}}, {"kind": "t3", "data": {"approved_at_utc": null, "subreddit": "dataengineering", "selftext": "", "author_fullname": "t2_8cr1i", "saved": false, "mod_reason_title": null, "gilded": 0, "clicked": false, "title": "The Parquet We Could Have", "link_flair_richtext": [], "subreddit_name_prefixed": "r/dataengineering", "hidden": false, "pwls": 6, "link_flair_css_class": "", "downs": 0, "thumbnail_height": null, "top_awarded_type": null, "hide_score": false, "name": "t3_190hyka", "quarantine": false, "link_flair_text_color": "light", "upvote_ratio": 0.86, "author_flair_background_color": null, "subreddit_type": "public", "ups": 5, "total_awards_received": 0, "media_embed": {}, "thumbnail_width": null, "author_flair_template_id": null, "is_original_content": false, "user_reports": [], "secure_media": null, "is_reddit_media_domain": false, "is_meta": false, "category": null, "secure_media_embed": {}, "link_flair_text": "Blog", "can_mod_post": false, "score": 5, "approved_by": null, "is_created_from_ads_ui": false, "author_premium": false, "thumbnail": "default", "edited": false, "author_flair_css_class": null, "author_flair_richtext": [], "gildings": {}, "content_categories": null, "is_self": false, "mod_note": null, "created": 1704596576.0, "link_flair_type": "text", "wls": 6, "removed_by_category": null, "banned_by": null, "author_flair_type": "text", "domain": "graphallthethings.com", "allow_live_comments": false, "selftext_html": null, "likes": null, "suggested_sort": null, "banned_at_utc": null, "url_overridden_by_dest": "https://graphallthethings.com/posts/the-parquet-we-could-have", "view_count": null, "archived": false, "no_follow": false, "is_crosspostable": false, "pinned": false, "over_18": false, "all_awardings": [], "awarders": [], "media_only": false, "link_flair_template_id": "eb739554-a7db-11eb-95d7-0ec0f8f30313", "can_gild": false, "spoiler": false, "locked": false, "author_flair_text": null, "treatment_tags": [], "visited": false, "removed_by": null, "num_reports": null, "distinguished": null, "subreddit_id": "t5_36en4", "author_is_blocked": false, "mod_reason_by": null, "removal_reason": null, "link_flair_background_color": "#0079d3", "id": "190hyka", "is_robot_indexable": true, "report_reasons": null, "author": "mwlon", "discussion_type": null, "num_comments": 0, "send_replies": true, "whitelist_status": "all_ads", "contest_mode": false, "mod_reports": [], "author_patreon_flair": false, "author_flair_text_color": null, "permalink": "/r/dataengineering/comments/190hyka/the_parquet_we_could_have/", "parent_whitelist_status": "all_ads", "stickied": false, "url": "https://graphallthethings.com/posts/the-parquet-we-could-have", "subreddit_subscribers": 151037, "created_utc": 1704596576.0, "num_crossposts": 0, "media": null, "is_video": false}}, {"kind": "t3", "data": {"approved_at_utc": null, "subreddit": "dataengineering", "selftext": "I m working on a data warehouse migration project from private database to cloud one. Basically I raw data will be uploaded on a S3 bucket and then we have to ingest it in snowflake cloud data warehouse. We are following S3&gt;Stage&gt;PSA&gt;DWH&gt;DMT layer.\n\nWhile ingesting data from S3 to stage we are facing a typical issue when there is bad data. Like for example there is country_cd column. And in stage we are taking it's data type Varchar(2). But in certain file vendor are mistakenly putting whole country name. That's why my code is breaking down. To ingesting file. \n\nAt present to we are using replace function to avoid that solution. But that is costly from time n cost perspective since raw data might contain billions of rows. \n\nYou people have lot of experience in data engineering. Can you provide some idea or lead, how do you overcome this issue. I don't want to send corrupt file back to vendor. Doing so will cost 2-3 days to the business. After every breakdown.", "author_fullname": "t2_1ubfs6x4", "saved": false, "mod_reason_title": null, "gilded": 0, "clicked": false, "title": "Issues in loading data from source to staging layer", "link_flair_richtext": [], "subreddit_name_prefixed": "r/dataengineering", "hidden": false, "pwls": 6, "link_flair_css_class": "", "downs": 0, "thumbnail_height": null, "top_awarded_type": null, "hide_score": false, "name": "t3_190pl8i", "quarantine": false, "link_flair_text_color": "light", "upvote_ratio": 0.7, "author_flair_background_color": null, "subreddit_type": "public", "ups": 4, "total_awards_received": 0, "media_embed": {}, "thumbnail_width": null, "author_flair_template_id": null, "is_original_content": false, "user_reports": [], "secure_media": null, "is_reddit_media_domain": false, "is_meta": false, "category": null, "secure_media_embed": {}, "link_flair_text": "Discussion", "can_mod_post": false, "score": 4, "approved_by": null, "is_created_from_ads_ui": false, "author_premium": false, "thumbnail": "self", "edited": false, "author_flair_css_class": null, "author_flair_richtext": [], "gildings": {}, "content_categories": null, "is_self": true, "mod_note": null, "created": 1704624438.0, "link_flair_type": "text", "wls": 6, "removed_by_category": null, "banned_by": null, "author_flair_type": "text", "domain": "self.dataengineering", "allow_live_comments": false, "selftext_html": "&lt;!-- SC_OFF --&gt;&lt;div class=\"md\"&gt;&lt;p&gt;I m working on a data warehouse migration project from private database to cloud one. Basically I raw data will be uploaded on a S3 bucket and then we have to ingest it in snowflake cloud data warehouse. We are following S3&amp;gt;Stage&amp;gt;PSA&amp;gt;DWH&amp;gt;DMT layer.&lt;/p&gt;\n\n&lt;p&gt;While ingesting data from S3 to stage we are facing a typical issue when there is bad data. Like for example there is country_cd column. And in stage we are taking it&amp;#39;s data type Varchar(2). But in certain file vendor are mistakenly putting whole country name. That&amp;#39;s why my code is breaking down. To ingesting file. &lt;/p&gt;\n\n&lt;p&gt;At present to we are using replace function to avoid that solution. But that is costly from time n cost perspective since raw data might contain billions of rows. &lt;/p&gt;\n\n&lt;p&gt;You people have lot of experience in data engineering. Can you provide some idea or lead, how do you overcome this issue. I don&amp;#39;t want to send corrupt file back to vendor. Doing so will cost 2-3 days to the business. After every breakdown.&lt;/p&gt;\n&lt;/div&gt;&lt;!-- SC_ON --&gt;", "likes": null, "suggested_sort": null, "banned_at_utc": null, "view_count": null, "archived": false, "no_follow": false, "is_crosspostable": false, "pinned": false, "over_18": false, "all_awardings": [], "awarders": [], "media_only": false, "link_flair_template_id": "92b74b58-aaca-11eb-b160-0e6181e3773f", "can_gild": false, "spoiler": false, "locked": false, "author_flair_text": null, "treatment_tags": [], "visited": false, "removed_by": null, "num_reports": null, "distinguished": null, "subreddit_id": "t5_36en4", "author_is_blocked": false, "mod_reason_by": null, "removal_reason": null, "link_flair_background_color": "#ff4500", "id": "190pl8i", "is_robot_indexable": true, "report_reasons": null, "author": "asud_w_asud", "discussion_type": null, "num_comments": 7, "send_replies": true, "whitelist_status": "all_ads", "contest_mode": false, "mod_reports": [], "author_patreon_flair": false, "author_flair_text_color": null, "permalink": "/r/dataengineering/comments/190pl8i/issues_in_loading_data_from_source_to_staging/", "parent_whitelist_status": "all_ads", "stickied": false, "url": "https://old.reddit.com/r/dataengineering/comments/190pl8i/issues_in_loading_data_from_source_to_staging/", "subreddit_subscribers": 151037, "created_utc": 1704624438.0, "num_crossposts": 0, "media": null, "is_video": false}}, {"kind": "t3", "data": {"approved_at_utc": null, "subreddit": "dataengineering", "selftext": "I am planning to take dbt certification exam , can you recommend any resources?", "author_fullname": "t2_ueliigs9", "saved": false, "mod_reason_title": null, "gilded": 0, "clicked": false, "title": "Dbt developer certification", "link_flair_richtext": [], "subreddit_name_prefixed": "r/dataengineering", "hidden": false, "pwls": 6, "link_flair_css_class": "", "downs": 0, "thumbnail_height": null, "top_awarded_type": null, "hide_score": false, "name": "t3_190trrs", "quarantine": false, "link_flair_text_color": "light", "upvote_ratio": 0.63, "author_flair_background_color": null, "subreddit_type": "public", "ups": 2, "total_awards_received": 0, "media_embed": {}, "thumbnail_width": null, "author_flair_template_id": null, "is_original_content": false, "user_reports": [], "secure_media": null, "is_reddit_media_domain": false, "is_meta": false, "category": null, "secure_media_embed": {}, "link_flair_text": "Discussion", "can_mod_post": false, "score": 2, "approved_by": null, "is_created_from_ads_ui": false, "author_premium": false, "thumbnail": "self", "edited": false, "author_flair_css_class": null, "author_flair_richtext": [], "gildings": {}, "content_categories": null, "is_self": true, "mod_note": null, "created": 1704639101.0, "link_flair_type": "text", "wls": 6, "removed_by_category": null, "banned_by": null, "author_flair_type": "text", "domain": "self.dataengineering", "allow_live_comments": false, "selftext_html": "&lt;!-- SC_OFF --&gt;&lt;div class=\"md\"&gt;&lt;p&gt;I am planning to take dbt certification exam , can you recommend any resources?&lt;/p&gt;\n&lt;/div&gt;&lt;!-- SC_ON --&gt;", "likes": null, "suggested_sort": null, "banned_at_utc": null, "view_count": null, "archived": false, "no_follow": false, "is_crosspostable": false, "pinned": false, "over_18": false, "all_awardings": [], "awarders": [], "media_only": false, "link_flair_template_id": "92b74b58-aaca-11eb-b160-0e6181e3773f", "can_gild": false, "spoiler": false, "locked": false, "author_flair_text": null, "treatment_tags": [], "visited": false, "removed_by": null, "num_reports": null, "distinguished": null, "subreddit_id": "t5_36en4", "author_is_blocked": false, "mod_reason_by": null, "removal_reason": null, "link_flair_background_color": "#ff4500", "id": "190trrs", "is_robot_indexable": true, "report_reasons": null, "author": "mamuonroll", "discussion_type": null, "num_comments": 1, "send_replies": true, "whitelist_status": "all_ads", "contest_mode": false, "mod_reports": [], "author_patreon_flair": false, "author_flair_text_color": null, "permalink": "/r/dataengineering/comments/190trrs/dbt_developer_certification/", "parent_whitelist_status": "all_ads", "stickied": false, "url": "https://old.reddit.com/r/dataengineering/comments/190trrs/dbt_developer_certification/", "subreddit_subscribers": 151037, "created_utc": 1704639101.0, "num_crossposts": 0, "media": null, "is_video": false}}, {"kind": "t3", "data": {"approved_at_utc": null, "subreddit": "dataengineering", "selftext": "I'd like to know if anyone has experience working in a similar setup or can provide insights into the infrastructure costs associated.\n\n\nMy main concern revolves around the potential costs of data transfer between AWS and Azure. Any experience, articles, presentations, blog posts would be helpful.\n\n\nThe architecture basically is SAP ERP &gt; AWS Snowflake &gt; Power BI.", "author_fullname": "t2_5etps", "saved": false, "mod_reason_title": null, "gilded": 0, "clicked": false, "title": "Data in amazon aws data viz in Power BI. Should I be so worried about data transfer costs?", "link_flair_richtext": [], "subreddit_name_prefixed": "r/dataengineering", "hidden": false, "pwls": 6, "link_flair_css_class": "", "downs": 0, "thumbnail_height": null, "top_awarded_type": null, "hide_score": false, "name": "t3_190ch5k", "quarantine": false, "link_flair_text_color": "light", "upvote_ratio": 0.76, "author_flair_background_color": null, "subreddit_type": "public", "ups": 2, "total_awards_received": 0, "media_embed": {}, "thumbnail_width": null, "author_flair_template_id": null, "is_original_content": false, "user_reports": [], "secure_media": null, "is_reddit_media_domain": false, "is_meta": false, "category": null, "secure_media_embed": {}, "link_flair_text": "Discussion", "can_mod_post": false, "score": 2, "approved_by": null, "is_created_from_ads_ui": false, "author_premium": false, "thumbnail": "self", "edited": 1704581489.0, "author_flair_css_class": null, "author_flair_richtext": [], "gildings": {}, "content_categories": null, "is_self": true, "mod_note": null, "created": 1704581078.0, "link_flair_type": "text", "wls": 6, "removed_by_category": null, "banned_by": null, "author_flair_type": "text", "domain": "self.dataengineering", "allow_live_comments": false, "selftext_html": "&lt;!-- SC_OFF --&gt;&lt;div class=\"md\"&gt;&lt;p&gt;I&amp;#39;d like to know if anyone has experience working in a similar setup or can provide insights into the infrastructure costs associated.&lt;/p&gt;\n\n&lt;p&gt;My main concern revolves around the potential costs of data transfer between AWS and Azure. Any experience, articles, presentations, blog posts would be helpful.&lt;/p&gt;\n\n&lt;p&gt;The architecture basically is SAP ERP &amp;gt; AWS Snowflake &amp;gt; Power BI.&lt;/p&gt;\n&lt;/div&gt;&lt;!-- SC_ON --&gt;", "likes": null, "suggested_sort": null, "banned_at_utc": null, "view_count": null, "archived": false, "no_follow": false, "is_crosspostable": false, "pinned": false, "over_18": false, "all_awardings": [], "awarders": [], "media_only": false, "link_flair_template_id": "92b74b58-aaca-11eb-b160-0e6181e3773f", "can_gild": false, "spoiler": false, "locked": false, "author_flair_text": null, "treatment_tags": [], "visited": false, "removed_by": null, "num_reports": null, "distinguished": null, "subreddit_id": "t5_36en4", "author_is_blocked": false, "mod_reason_by": null, "removal_reason": null, "link_flair_background_color": "#ff4500", "id": "190ch5k", "is_robot_indexable": true, "report_reasons": null, "author": "brunudumal", "discussion_type": null, "num_comments": 3, "send_replies": true, "whitelist_status": "all_ads", "contest_mode": false, "mod_reports": [], "author_patreon_flair": false, "author_flair_text_color": null, "permalink": "/r/dataengineering/comments/190ch5k/data_in_amazon_aws_data_viz_in_power_bi_should_i/", "parent_whitelist_status": "all_ads", "stickied": false, "url": "https://old.reddit.com/r/dataengineering/comments/190ch5k/data_in_amazon_aws_data_viz_in_power_bi_should_i/", "subreddit_subscribers": 151037, "created_utc": 1704581078.0, "num_crossposts": 0, "media": null, "is_video": false}}, {"kind": "t3", "data": {"approved_at_utc": null, "subreddit": "dataengineering", "selftext": "Greetings!\n\nI'm currently seeking advice on generating materialized views from OpenAPI/JSON Schema. Are there recommended tools or best practices for achieving this without manual conversions/reinventing the wheel? \n\nMore details: we have an OpenAPI YML schema that describes what kind of data arrives from the product to the S3 server. And from it, to the database.\n\nWe convert the YML to JSON Schema for the validator to deploy, and, fetched from the S3 and validated against that JSON Schema protocol, the data comes to our ClickHouse database. We have different versions of the protocol, and we select the particular version based on the \"version\" field in the data.\n\nAnd so we get the validated/unvalidated raw data. But we need to parse the huge JSON that comprises the most information, with all the game analytics fields and such. At the moment, we write Materialized Views for this task manually. All of the information needed for writing these MatViews is contained withing the protocol, but we do not use it.\n\nI was thinking of writing a Python script that would generate these views based on the JSON Schema variant of the protocol. This is kinda intuitive, and based on the actual data that the validator processes.\n\nBut still I wonder. I doubt that I am the only one who got a task like that in the whole industry. Are there any tools, or maybe best practices, to accomplish that task?\n\nYour insights are highly appreciated. \n\nThank you!", "author_fullname": "t2_4rd2b7yy", "saved": false, "mod_reason_title": null, "gilded": 0, "clicked": false, "title": "Seeking Advice: Automating ClickHouse Views from JSON Schema/OpenAPI", "link_flair_richtext": [], "subreddit_name_prefixed": "r/dataengineering", "hidden": false, "pwls": 6, "link_flair_css_class": "", "downs": 0, "thumbnail_height": null, "top_awarded_type": null, "hide_score": true, "name": "t3_190ztmw", "quarantine": false, "link_flair_text_color": "light", "upvote_ratio": 0.5, "author_flair_background_color": null, "subreddit_type": "public", "ups": 0, "total_awards_received": 0, "media_embed": {}, "thumbnail_width": null, "author_flair_template_id": null, "is_original_content": false, "user_reports": [], "secure_media": null, "is_reddit_media_domain": false, "is_meta": false, "category": null, "secure_media_embed": {}, "link_flair_text": "Help", "can_mod_post": false, "score": 0, "approved_by": null, "is_created_from_ads_ui": false, "author_premium": false, "thumbnail": "self", "edited": false, "author_flair_css_class": null, "author_flair_richtext": [], "gildings": {}, "content_categories": null, "is_self": true, "mod_note": null, "created": 1704654883.0, "link_flair_type": "text", "wls": 6, "removed_by_category": null, "banned_by": null, "author_flair_type": "text", "domain": "self.dataengineering", "allow_live_comments": false, "selftext_html": "&lt;!-- SC_OFF --&gt;&lt;div class=\"md\"&gt;&lt;p&gt;Greetings!&lt;/p&gt;\n\n&lt;p&gt;I&amp;#39;m currently seeking advice on generating materialized views from OpenAPI/JSON Schema. Are there recommended tools or best practices for achieving this without manual conversions/reinventing the wheel? &lt;/p&gt;\n\n&lt;p&gt;More details: we have an OpenAPI YML schema that describes what kind of data arrives from the product to the S3 server. And from it, to the database.&lt;/p&gt;\n\n&lt;p&gt;We convert the YML to JSON Schema for the validator to deploy, and, fetched from the S3 and validated against that JSON Schema protocol, the data comes to our ClickHouse database. We have different versions of the protocol, and we select the particular version based on the &amp;quot;version&amp;quot; field in the data.&lt;/p&gt;\n\n&lt;p&gt;And so we get the validated/unvalidated raw data. But we need to parse the huge JSON that comprises the most information, with all the game analytics fields and such. At the moment, we write Materialized Views for this task manually. All of the information needed for writing these MatViews is contained withing the protocol, but we do not use it.&lt;/p&gt;\n\n&lt;p&gt;I was thinking of writing a Python script that would generate these views based on the JSON Schema variant of the protocol. This is kinda intuitive, and based on the actual data that the validator processes.&lt;/p&gt;\n\n&lt;p&gt;But still I wonder. I doubt that I am the only one who got a task like that in the whole industry. Are there any tools, or maybe best practices, to accomplish that task?&lt;/p&gt;\n\n&lt;p&gt;Your insights are highly appreciated. &lt;/p&gt;\n\n&lt;p&gt;Thank you!&lt;/p&gt;\n&lt;/div&gt;&lt;!-- SC_ON --&gt;", "likes": null, "suggested_sort": null, "banned_at_utc": null, "view_count": null, "archived": false, "no_follow": true, "is_crosspostable": false, "pinned": false, "over_18": false, "all_awardings": [], "awarders": [], "media_only": false, "link_flair_template_id": "2ca94cd6-ac27-11eb-a8eb-0e7f457f5bd3", "can_gild": false, "spoiler": false, "locked": false, "author_flair_text": null, "treatment_tags": [], "visited": false, "removed_by": null, "num_reports": null, "distinguished": null, "subreddit_id": "t5_36en4", "author_is_blocked": false, "mod_reason_by": null, "removal_reason": null, "link_flair_background_color": "#ea0027", "id": "190ztmw", "is_robot_indexable": true, "report_reasons": null, "author": "soltiamosamita", "discussion_type": null, "num_comments": 0, "send_replies": true, "whitelist_status": "all_ads", "contest_mode": false, "mod_reports": [], "author_patreon_flair": false, "author_flair_text_color": null, "permalink": "/r/dataengineering/comments/190ztmw/seeking_advice_automating_clickhouse_views_from/", "parent_whitelist_status": "all_ads", "stickied": false, "url": "https://old.reddit.com/r/dataengineering/comments/190ztmw/seeking_advice_automating_clickhouse_views_from/", "subreddit_subscribers": 151037, "created_utc": 1704654883.0, "num_crossposts": 0, "media": null, "is_video": false}}, {"kind": "t3", "data": {"approved_at_utc": null, "subreddit": "dataengineering", "selftext": "Looking for reviews on this course. I am trying to join a course which has case study approach to teaching SQL, I want to solve most real-world problems as possible to gain more confidence when working with SQL or when getting interviewed on it. Thanks for your input.", "author_fullname": "t2_6dym6exn", "saved": false, "mod_reason_title": null, "gilded": 0, "clicked": false, "title": "Review for Serious SQL course (Data With Danny )?", "link_flair_richtext": [], "subreddit_name_prefixed": "r/dataengineering", "hidden": false, "pwls": 6, "link_flair_css_class": "", "downs": 0, "thumbnail_height": null, "top_awarded_type": null, "hide_score": false, "name": "t3_190i0sh", "quarantine": false, "link_flair_text_color": "light", "upvote_ratio": 0.67, "author_flair_background_color": null, "subreddit_type": "public", "ups": 1, "total_awards_received": 0, "media_embed": {}, "thumbnail_width": null, "author_flair_template_id": null, "is_original_content": false, "user_reports": [], "secure_media": null, "is_reddit_media_domain": false, "is_meta": false, "category": null, "secure_media_embed": {}, "link_flair_text": "Discussion", "can_mod_post": false, "score": 1, "approved_by": null, "is_created_from_ads_ui": false, "author_premium": false, "thumbnail": "self", "edited": false, "author_flair_css_class": null, "author_flair_richtext": [], "gildings": {}, "content_categories": null, "is_self": true, "mod_note": null, "created": 1704596767.0, "link_flair_type": "text", "wls": 6, "removed_by_category": null, "banned_by": null, "author_flair_type": "text", "domain": "self.dataengineering", "allow_live_comments": false, "selftext_html": "&lt;!-- SC_OFF --&gt;&lt;div class=\"md\"&gt;&lt;p&gt;Looking for reviews on this course. I am trying to join a course which has case study approach to teaching SQL, I want to solve most real-world problems as possible to gain more confidence when working with SQL or when getting interviewed on it. Thanks for your input.&lt;/p&gt;\n&lt;/div&gt;&lt;!-- SC_ON --&gt;", "likes": null, "suggested_sort": null, "banned_at_utc": null, "view_count": null, "archived": false, "no_follow": true, "is_crosspostable": false, "pinned": false, "over_18": false, "all_awardings": [], "awarders": [], "media_only": false, "link_flair_template_id": "92b74b58-aaca-11eb-b160-0e6181e3773f", "can_gild": false, "spoiler": false, "locked": false, "author_flair_text": null, "treatment_tags": [], "visited": false, "removed_by": null, "num_reports": null, "distinguished": null, "subreddit_id": "t5_36en4", "author_is_blocked": false, "mod_reason_by": null, "removal_reason": null, "link_flair_background_color": "#ff4500", "id": "190i0sh", "is_robot_indexable": true, "report_reasons": null, "author": "StatusStar", "discussion_type": null, "num_comments": 1, "send_replies": true, "whitelist_status": "all_ads", "contest_mode": false, "mod_reports": [], "author_patreon_flair": false, "author_flair_text_color": null, "permalink": "/r/dataengineering/comments/190i0sh/review_for_serious_sql_course_data_with_danny/", "parent_whitelist_status": "all_ads", "stickied": false, "url": "https://old.reddit.com/r/dataengineering/comments/190i0sh/review_for_serious_sql_course_data_with_danny/", "subreddit_subscribers": 151037, "created_utc": 1704596767.0, "num_crossposts": 0, "media": null, "is_video": false}}, {"kind": "t3", "data": {"approved_at_utc": null, "subreddit": "dataengineering", "selftext": "", "author_fullname": "t2_j1toq", "saved": false, "mod_reason_title": null, "gilded": 0, "clicked": false, "title": "Architecting Global Data Collaboration with Delta Sharing", "link_flair_richtext": [], "subreddit_name_prefixed": "r/dataengineering", "hidden": false, "pwls": 6, "link_flair_css_class": "", "downs": 0, "thumbnail_height": 73, "top_awarded_type": null, "hide_score": false, "name": "t3_190go68", "quarantine": false, "link_flair_text_color": "light", "upvote_ratio": 0.67, "author_flair_background_color": null, "ups": 1, "total_awards_received": 0, "media_embed": {}, "thumbnail_width": 140, "author_flair_template_id": null, "is_original_content": false, "user_reports": [], "secure_media": null, "is_reddit_media_domain": false, "is_meta": false, "category": null, "secure_media_embed": {}, "link_flair_text": "Blog", "can_mod_post": false, "score": 1, "approved_by": null, "is_created_from_ads_ui": false, "author_premium": false, "thumbnail": "https://b.thumbs.redditmedia.com/gFneKKiXjQ3xhXeq2NV21XS0djaZYcgQcKXm9EUvXMU.jpg", "edited": false, "author_flair_css_class": null, "author_flair_richtext": [], "gildings": {}, "post_hint": "link", "content_categories": null, "is_self": false, "subreddit_type": "public", "created": 1704592676.0, "link_flair_type": "text", "wls": 6, "removed_by_category": null, "banned_by": null, "author_flair_type": "text", "domain": "databricks.com", "allow_live_comments": false, "selftext_html": null, "likes": null, "suggested_sort": null, "banned_at_utc": null, "url_overridden_by_dest": "https://www.databricks.com/blog/architecting-global-data-collaboration-delta-sharing", "view_count": null, "archived": false, "no_follow": true, "is_crosspostable": false, "pinned": false, "over_18": false, "preview": {"images": [{"source": {"url": "https://external-preview.redd.it/bcAraGz4mjrpzNUJUNwggQqY3DtavPvuMqPv1nz9ulo.jpg?auto=webp&amp;s=5dffea24607781b64a311818afc2bb3f0c3707b5", "width": 1200, "height": 628}, "resolutions": [{"url": "https://external-preview.redd.it/bcAraGz4mjrpzNUJUNwggQqY3DtavPvuMqPv1nz9ulo.jpg?width=108&amp;crop=smart&amp;auto=webp&amp;s=37e1442e01f82dc5e9c77c05a86a6164bd8d163d", "width": 108, "height": 56}, {"url": "https://external-preview.redd.it/bcAraGz4mjrpzNUJUNwggQqY3DtavPvuMqPv1nz9ulo.jpg?width=216&amp;crop=smart&amp;auto=webp&amp;s=9aaaf601f3143341ee95c2da696e5078dd5b6aab", "width": 216, "height": 113}, {"url": "https://external-preview.redd.it/bcAraGz4mjrpzNUJUNwggQqY3DtavPvuMqPv1nz9ulo.jpg?width=320&amp;crop=smart&amp;auto=webp&amp;s=0e20a5ff327d4646ff752a729644954ece4abb61", "width": 320, "height": 167}, {"url": "https://external-preview.redd.it/bcAraGz4mjrpzNUJUNwggQqY3DtavPvuMqPv1nz9ulo.jpg?width=640&amp;crop=smart&amp;auto=webp&amp;s=a7b43afc8813bc0c982f5e653004cc050242c8ec", "width": 640, "height": 334}, {"url": "https://external-preview.redd.it/bcAraGz4mjrpzNUJUNwggQqY3DtavPvuMqPv1nz9ulo.jpg?width=960&amp;crop=smart&amp;auto=webp&amp;s=5dc45af09a55420ef110d6445b5786e70982a34e", "width": 960, "height": 502}, {"url": "https://external-preview.redd.it/bcAraGz4mjrpzNUJUNwggQqY3DtavPvuMqPv1nz9ulo.jpg?width=1080&amp;crop=smart&amp;auto=webp&amp;s=5ec73812481fbe763078c6752e8bc481dd42c455", "width": 1080, "height": 565}], "variants": {}, "id": "rfazbKE2R40unqZc5UYxtOAqABsl810v3opdGLsLj9s"}], "enabled": false}, "all_awardings": [], "awarders": [], "media_only": false, "link_flair_template_id": "eb739554-a7db-11eb-95d7-0ec0f8f30313", "can_gild": false, "spoiler": false, "locked": false, "author_flair_text": null, "treatment_tags": [], "visited": false, "removed_by": null, "mod_note": null, "distinguished": null, "subreddit_id": "t5_36en4", "author_is_blocked": false, "mod_reason_by": null, "num_reports": null, "removal_reason": null, "link_flair_background_color": "#0079d3", "id": "190go68", "is_robot_indexable": true, "report_reasons": null, "author": "mjgcfb", "discussion_type": null, "num_comments": 0, "send_replies": true, "whitelist_status": "all_ads", "contest_mode": false, "mod_reports": [], "author_patreon_flair": false, "author_flair_text_color": null, "permalink": "/r/dataengineering/comments/190go68/architecting_global_data_collaboration_with_delta/", "parent_whitelist_status": "all_ads", "stickied": false, "url": "https://www.databricks.com/blog/architecting-global-data-collaboration-delta-sharing", "subreddit_subscribers": 151037, "created_utc": 1704592676.0, "num_crossposts": 0, "media": null, "is_video": false}}, {"kind": "t3", "data": {"approved_at_utc": null, "subreddit": "dataengineering", "selftext": "TLDR: Trying to figure out if it\u2019s a terrible career move to go from Analytics Engineer (technically Data Engineer job title) to Senior Data Analyst.\n\n\nBackground:\n- Have BS and MS in Engineering\n- Worked for an airframer (like Boeing, Lockheed, etc). Loved it. Job was analyzing manufactured parts, but lots of SQL data analysis.\n- After 6 years was making $90k\n- Left for fully remote tech company that does online retail, after two years at tech company, make $140k\n- Current job is \u201cdata engineer\u201d but really Analytics Engineer. 95% SQL, dbt, fivetran, Snowflake. This has me worried about career growth because I\u2019m not actually learning Data Engineering, so the high pay DE jobs that need streaming/kafka, heavy python, spark, etc all seem out of reach.\n\n\nI\u2019m now getting recruited by an airline to join them as a Senior Data Analyst. Pay would go down to $130k.\n\n\nPros of taking new job:\n- It\u2019s an industry I\u2019m passionate about\n- I\u2019m best and happiest doing business analytics questions anyway (building pipelines, the rare times I do, is dull. Answering business questions is fun. Also I\u2019m a people person.) \n- Unlimited standby travel perks\n- I see a path for eventual career advancement to management, maybe onward to VP etc.\n\n\nCons of taking new job:\n- Hybrid\n- Corporate bloat/HR/etc\n- $10k pay cut\n\n\nPros of keeping current job:\n- They love me at the tech startup. It\u2019s also 100% remote and easy work I do well.\n- Gotten good raises every year I\u2019ve been there.\n- Pay for data/analytics engineers is obviously generally higher than for analysts.\n\n\nCons of current job:\n- Stagnating in current job skill wise. Also career wise because we\u2019re a small team, so pay raises keep coming but there\u2019s no one else in Data to manage or move into a leadership position over.\n\n\nWould I be limiting future career/salary by going DE -&gt; DA? Everyone seems to be trying to go the opposite direction!", "author_fullname": "t2_eqjfj6joh", "saved": false, "mod_reason_title": null, "gilded": 0, "clicked": false, "title": "Crazy to go from DE/AE -&gt; DA?", "link_flair_richtext": [], "subreddit_name_prefixed": "r/dataengineering", "hidden": false, "pwls": 6, "link_flair_css_class": "", "downs": 0, "thumbnail_height": null, "top_awarded_type": null, "hide_score": false, "name": "t3_190fzgv", "quarantine": false, "link_flair_text_color": "light", "upvote_ratio": 1.0, "author_flair_background_color": null, "subreddit_type": "public", "ups": 1, "total_awards_received": 0, "media_embed": {}, "thumbnail_width": null, "author_flair_template_id": null, "is_original_content": false, "user_reports": [], "secure_media": null, "is_reddit_media_domain": false, "is_meta": false, "category": null, "secure_media_embed": {}, "link_flair_text": "Career", "can_mod_post": false, "score": 1, "approved_by": null, "is_created_from_ads_ui": false, "author_premium": false, "thumbnail": "self", "edited": false, "author_flair_css_class": null, "author_flair_richtext": [], "gildings": {}, "content_categories": null, "is_self": true, "mod_note": null, "created": 1704590670.0, "link_flair_type": "text", "wls": 6, "removed_by_category": null, "banned_by": null, "author_flair_type": "text", "domain": "self.dataengineering", "allow_live_comments": false, "selftext_html": "&lt;!-- SC_OFF --&gt;&lt;div class=\"md\"&gt;&lt;p&gt;TLDR: Trying to figure out if it\u2019s a terrible career move to go from Analytics Engineer (technically Data Engineer job title) to Senior Data Analyst.&lt;/p&gt;\n\n&lt;p&gt;Background:\n- Have BS and MS in Engineering\n- Worked for an airframer (like Boeing, Lockheed, etc). Loved it. Job was analyzing manufactured parts, but lots of SQL data analysis.\n- After 6 years was making $90k\n- Left for fully remote tech company that does online retail, after two years at tech company, make $140k\n- Current job is \u201cdata engineer\u201d but really Analytics Engineer. 95% SQL, dbt, fivetran, Snowflake. This has me worried about career growth because I\u2019m not actually learning Data Engineering, so the high pay DE jobs that need streaming/kafka, heavy python, spark, etc all seem out of reach.&lt;/p&gt;\n\n&lt;p&gt;I\u2019m now getting recruited by an airline to join them as a Senior Data Analyst. Pay would go down to $130k.&lt;/p&gt;\n\n&lt;p&gt;Pros of taking new job:\n- It\u2019s an industry I\u2019m passionate about\n- I\u2019m best and happiest doing business analytics questions anyway (building pipelines, the rare times I do, is dull. Answering business questions is fun. Also I\u2019m a people person.) \n- Unlimited standby travel perks\n- I see a path for eventual career advancement to management, maybe onward to VP etc.&lt;/p&gt;\n\n&lt;p&gt;Cons of taking new job:\n- Hybrid\n- Corporate bloat/HR/etc\n- $10k pay cut&lt;/p&gt;\n\n&lt;p&gt;Pros of keeping current job:\n- They love me at the tech startup. It\u2019s also 100% remote and easy work I do well.\n- Gotten good raises every year I\u2019ve been there.\n- Pay for data/analytics engineers is obviously generally higher than for analysts.&lt;/p&gt;\n\n&lt;p&gt;Cons of current job:\n- Stagnating in current job skill wise. Also career wise because we\u2019re a small team, so pay raises keep coming but there\u2019s no one else in Data to manage or move into a leadership position over.&lt;/p&gt;\n\n&lt;p&gt;Would I be limiting future career/salary by going DE -&amp;gt; DA? Everyone seems to be trying to go the opposite direction!&lt;/p&gt;\n&lt;/div&gt;&lt;!-- SC_ON --&gt;", "likes": null, "suggested_sort": null, "banned_at_utc": null, "view_count": null, "archived": false, "no_follow": true, "is_crosspostable": false, "pinned": false, "over_18": false, "all_awardings": [], "awarders": [], "media_only": false, "link_flair_template_id": "069dd614-a7dc-11eb-8e48-0e90f49436a3", "can_gild": false, "spoiler": false, "locked": false, "author_flair_text": null, "treatment_tags": [], "visited": false, "removed_by": null, "num_reports": null, "distinguished": null, "subreddit_id": "t5_36en4", "author_is_blocked": false, "mod_reason_by": null, "removal_reason": null, "link_flair_background_color": "#349e48", "id": "190fzgv", "is_robot_indexable": true, "report_reasons": null, "author": "LiterallyNotUsername", "discussion_type": null, "num_comments": 0, "send_replies": true, "whitelist_status": "all_ads", "contest_mode": false, "mod_reports": [], "author_patreon_flair": false, "author_flair_text_color": null, "permalink": "/r/dataengineering/comments/190fzgv/crazy_to_go_from_deae_da/", "parent_whitelist_status": "all_ads", "stickied": false, "url": "https://old.reddit.com/r/dataengineering/comments/190fzgv/crazy_to_go_from_deae_da/", "subreddit_subscribers": 151037, "created_utc": 1704590670.0, "num_crossposts": 0, "media": null, "is_video": false}}, {"kind": "t3", "data": {"approved_at_utc": null, "subreddit": "dataengineering", "selftext": "My new work is conne tors deployement and I never worked on that. Anyone has experienece of connectors deployement or any material/ course to learn this? Tried searching online I didn't find much. Please guide me if you know .\nThanks", "author_fullname": "t2_nlmrmy2ow", "saved": false, "mod_reason_title": null, "gilded": 0, "clicked": false, "title": "connectors deployment", "link_flair_richtext": [], "subreddit_name_prefixed": "r/dataengineering", "hidden": false, "pwls": 6, "link_flair_css_class": "", "downs": 0, "thumbnail_height": null, "top_awarded_type": null, "hide_score": false, "name": "t3_190pmdj", "quarantine": false, "link_flair_text_color": "light", "upvote_ratio": 0.33, "author_flair_background_color": null, "subreddit_type": "public", "ups": 0, "total_awards_received": 0, "media_embed": {}, "thumbnail_width": null, "author_flair_template_id": null, "is_original_content": false, "user_reports": [], "secure_media": null, "is_reddit_media_domain": false, "is_meta": false, "category": null, "secure_media_embed": {}, "link_flair_text": "Help", "can_mod_post": false, "score": 0, "approved_by": null, "is_created_from_ads_ui": false, "author_premium": false, "thumbnail": "self", "edited": false, "author_flair_css_class": null, "author_flair_richtext": [], "gildings": {}, "content_categories": null, "is_self": true, "mod_note": null, "created": 1704624572.0, "link_flair_type": "text", "wls": 6, "removed_by_category": null, "banned_by": null, "author_flair_type": "text", "domain": "self.dataengineering", "allow_live_comments": false, "selftext_html": "&lt;!-- SC_OFF --&gt;&lt;div class=\"md\"&gt;&lt;p&gt;My new work is conne tors deployement and I never worked on that. Anyone has experienece of connectors deployement or any material/ course to learn this? Tried searching online I didn&amp;#39;t find much. Please guide me if you know .\nThanks&lt;/p&gt;\n&lt;/div&gt;&lt;!-- SC_ON --&gt;", "likes": null, "suggested_sort": null, "banned_at_utc": null, "view_count": null, "archived": false, "no_follow": true, "is_crosspostable": false, "pinned": false, "over_18": false, "all_awardings": [], "awarders": [], "media_only": false, "link_flair_template_id": "2ca94cd6-ac27-11eb-a8eb-0e7f457f5bd3", "can_gild": false, "spoiler": false, "locked": false, "author_flair_text": null, "treatment_tags": [], "visited": false, "removed_by": null, "num_reports": null, "distinguished": null, "subreddit_id": "t5_36en4", "author_is_blocked": false, "mod_reason_by": null, "removal_reason": null, "link_flair_background_color": "#ea0027", "id": "190pmdj", "is_robot_indexable": true, "report_reasons": null, "author": "Sufficient_Koala_609", "discussion_type": null, "num_comments": 1, "send_replies": true, "whitelist_status": "all_ads", "contest_mode": false, "mod_reports": [], "author_patreon_flair": false, "author_flair_text_color": null, "permalink": "/r/dataengineering/comments/190pmdj/connectors_deployment/", "parent_whitelist_status": "all_ads", "stickied": false, "url": "https://old.reddit.com/r/dataengineering/comments/190pmdj/connectors_deployment/", "subreddit_subscribers": 151037, "created_utc": 1704624572.0, "num_crossposts": 0, "media": null, "is_video": false}}, {"kind": "t3", "data": {"approved_at_utc": null, "subreddit": "dataengineering", "selftext": "Hello everyone. Maybe this sounds silly, but I've been working at a data startup for 2 years. I have worked with Python, PySpark, SQL, multiple AWS services, DBT, and several other things. However, the company lacks good practices, and thanks to my good performance, I am increasingly taking a greater role in the projects.\n\nIs it foolish to have a feeling that the project is \"a time bomb\", believing that at any moment it can explode? Is it something normal?\n\nFinally, if you can recommend ways to learn best practices, or at least what the basics are for a project to be well put together from the beginning, that would be great. (courses, books, YouTube channels, etc.)", "author_fullname": "t2_d6unb95b", "saved": false, "mod_reason_title": null, "gilded": 0, "clicked": false, "title": "I just want to be a good DE", "link_flair_richtext": [], "subreddit_name_prefixed": "r/dataengineering", "hidden": false, "pwls": 6, "link_flair_css_class": "", "downs": 0, "thumbnail_height": null, "top_awarded_type": null, "hide_score": true, "name": "t3_1910hct", "quarantine": false, "link_flair_text_color": "light", "upvote_ratio": 0.2, "author_flair_background_color": null, "subreddit_type": "public", "ups": 0, "total_awards_received": 0, "media_embed": {}, "thumbnail_width": null, "author_flair_template_id": null, "is_original_content": false, "user_reports": [], "secure_media": null, "is_reddit_media_domain": false, "is_meta": false, "category": null, "secure_media_embed": {}, "link_flair_text": "Career", "can_mod_post": false, "score": 0, "approved_by": null, "is_created_from_ads_ui": false, "author_premium": false, "thumbnail": "self", "edited": false, "author_flair_css_class": null, "author_flair_richtext": [], "gildings": {}, "content_categories": null, "is_self": true, "mod_note": null, "created": 1704656560.0, "link_flair_type": "text", "wls": 6, "removed_by_category": null, "banned_by": null, "author_flair_type": "text", "domain": "self.dataengineering", "allow_live_comments": false, "selftext_html": "&lt;!-- SC_OFF --&gt;&lt;div class=\"md\"&gt;&lt;p&gt;Hello everyone. Maybe this sounds silly, but I&amp;#39;ve been working at a data startup for 2 years. I have worked with Python, PySpark, SQL, multiple AWS services, DBT, and several other things. However, the company lacks good practices, and thanks to my good performance, I am increasingly taking a greater role in the projects.&lt;/p&gt;\n\n&lt;p&gt;Is it foolish to have a feeling that the project is &amp;quot;a time bomb&amp;quot;, believing that at any moment it can explode? Is it something normal?&lt;/p&gt;\n\n&lt;p&gt;Finally, if you can recommend ways to learn best practices, or at least what the basics are for a project to be well put together from the beginning, that would be great. (courses, books, YouTube channels, etc.)&lt;/p&gt;\n&lt;/div&gt;&lt;!-- SC_ON --&gt;", "likes": null, "suggested_sort": null, "banned_at_utc": null, "view_count": null, "archived": false, "no_follow": true, "is_crosspostable": false, "pinned": false, "over_18": false, "all_awardings": [], "awarders": [], "media_only": false, "link_flair_template_id": "069dd614-a7dc-11eb-8e48-0e90f49436a3", "can_gild": false, "spoiler": false, "locked": false, "author_flair_text": null, "treatment_tags": [], "visited": false, "removed_by": null, "num_reports": null, "distinguished": null, "subreddit_id": "t5_36en4", "author_is_blocked": false, "mod_reason_by": null, "removal_reason": null, "link_flair_background_color": "#349e48", "id": "1910hct", "is_robot_indexable": true, "report_reasons": null, "author": "ArgenZet", "discussion_type": null, "num_comments": 2, "send_replies": true, "whitelist_status": "all_ads", "contest_mode": false, "mod_reports": [], "author_patreon_flair": false, "author_flair_text_color": null, "permalink": "/r/dataengineering/comments/1910hct/i_just_want_to_be_a_good_de/", "parent_whitelist_status": "all_ads", "stickied": false, "url": "https://old.reddit.com/r/dataengineering/comments/1910hct/i_just_want_to_be_a_good_de/", "subreddit_subscribers": 151037, "created_utc": 1704656560.0, "num_crossposts": 0, "media": null, "is_video": false}}, {"kind": "t3", "data": {"approved_at_utc": null, "subreddit": "dataengineering", "selftext": "Hey Fellas,\n\nI\u2019ll keep it short. I\u2019m trying to create an outstanding connections on Linkedin. So, can everyone plz suggest me Linkedin accounts of Prodigies in Data Engineering whose posts, Blogs, youtube channels can help ACE Data engineering role.", "author_fullname": "t2_tqybxh5z", "saved": false, "mod_reason_title": null, "gilded": 0, "clicked": false, "title": "List of Experts in Data Engineering on Linkedin.!!", "link_flair_richtext": [], "subreddit_name_prefixed": "r/dataengineering", "hidden": false, "pwls": 6, "link_flair_css_class": "", "downs": 0, "thumbnail_height": null, "top_awarded_type": null, "hide_score": false, "name": "t3_190ygby", "quarantine": false, "link_flair_text_color": "light", "upvote_ratio": 0.3, "author_flair_background_color": null, "subreddit_type": "public", "ups": 0, "total_awards_received": 0, "media_embed": {}, "thumbnail_width": null, "author_flair_template_id": null, "is_original_content": false, "user_reports": [], "secure_media": null, "is_reddit_media_domain": false, "is_meta": false, "category": null, "secure_media_embed": {}, "link_flair_text": "Discussion", "can_mod_post": false, "score": 0, "approved_by": null, "is_created_from_ads_ui": false, "author_premium": false, "thumbnail": "self", "edited": false, "author_flair_css_class": null, "author_flair_richtext": [], "gildings": {}, "content_categories": null, "is_self": true, "mod_note": null, "created": 1704651441.0, "link_flair_type": "text", "wls": 6, "removed_by_category": null, "banned_by": null, "author_flair_type": "text", "domain": "self.dataengineering", "allow_live_comments": false, "selftext_html": "&lt;!-- SC_OFF --&gt;&lt;div class=\"md\"&gt;&lt;p&gt;Hey Fellas,&lt;/p&gt;\n\n&lt;p&gt;I\u2019ll keep it short. I\u2019m trying to create an outstanding connections on Linkedin. So, can everyone plz suggest me Linkedin accounts of Prodigies in Data Engineering whose posts, Blogs, youtube channels can help ACE Data engineering role.&lt;/p&gt;\n&lt;/div&gt;&lt;!-- SC_ON --&gt;", "likes": null, "suggested_sort": null, "banned_at_utc": null, "view_count": null, "archived": false, "no_follow": true, "is_crosspostable": false, "pinned": false, "over_18": false, "all_awardings": [], "awarders": [], "media_only": false, "link_flair_template_id": "92b74b58-aaca-11eb-b160-0e6181e3773f", "can_gild": false, "spoiler": false, "locked": false, "author_flair_text": null, "treatment_tags": [], "visited": false, "removed_by": null, "num_reports": null, "distinguished": null, "subreddit_id": "t5_36en4", "author_is_blocked": false, "mod_reason_by": null, "removal_reason": null, "link_flair_background_color": "#ff4500", "id": "190ygby", "is_robot_indexable": true, "report_reasons": null, "author": "rajveersolanki9", "discussion_type": null, "num_comments": 1, "send_replies": true, "whitelist_status": "all_ads", "contest_mode": false, "mod_reports": [], "author_patreon_flair": false, "author_flair_text_color": null, "permalink": "/r/dataengineering/comments/190ygby/list_of_experts_in_data_engineering_on_linkedin/", "parent_whitelist_status": "all_ads", "stickied": false, "url": "https://old.reddit.com/r/dataengineering/comments/190ygby/list_of_experts_in_data_engineering_on_linkedin/", "subreddit_subscribers": 151037, "created_utc": 1704651441.0, "num_crossposts": 0, "media": null, "is_video": false}}], "before": null}}